pyulid/__init__.py
pyulid/py.typed
pyulid/pyulid.pypy39-pp73-ppc_64-linux-gnu.so
ulid_python-1.0.1.dist-info/METADATA
ulid_python-1.0.1.dist-info/WHEEL
ulid_python-1.0.1.dist-info/licenses/LICENSE
ulid_python-1.0.1.dist-info/RECORD
