Metadata-Version: 2.4
Name: ulid-python
Version: 1.0.1
Classifier: Development Status :: 5 - Production/Stable
Classifier: Intended Audience :: Developers
Classifier: License :: OSI Approved :: MIT License
Classifier: Programming Language :: Python :: 3
Classifier: Programming Language :: Python :: 3.8
Classifier: Programming Language :: Python :: 3.9
Classifier: Programming Language :: Python :: 3.10
Classifier: Programming Language :: Python :: 3.11
Classifier: Programming Language :: Python :: 3.12
Classifier: Programming Language :: Python :: 3.13
Classifier: Programming Language :: Rust
Classifier: Programming Language :: Python :: Implementation :: CPython
Classifier: Programming Language :: Python :: Implementation :: PyPy
Classifier: Topic :: Software Development :: Libraries :: Python Modules
Classifier: Topic :: Utilities
Requires-Dist: typing-extensions ; python_full_version < '3.10'
Requires-Dist: pytest>=6.0 ; extra == 'test'
Requires-Dist: pytest>=6.0 ; extra == 'dev'
Requires-Dist: ruff ; extra == 'dev'
Provides-Extra: test
Provides-Extra: dev
License-File: LICENSE
Summary: ULID (Universally Unique Lexicographically Sortable Identifier) implementation for Python - a better alternative to UUIDv4
Keywords: ulid,uuid,identifier,sortable,rust
Author: Yoseph Bernandus
Requires-Python: >=3.8
